pinnacle_cli/__init__.py
pinnacle_cli/admin.py
pinnacle_cli/constants.py
pinnacle_cli/dist_files/lambda_function.py
pinnacle_cli/examples/hello_world.py
pinnacle_cli/main.py
pinnacle_cli/openapi/__init__.py
pinnacle_cli/openapi/app.py
pinnacle_cli/proxy/README.md
pinnacle_cli/proxy/__init__.py
pinnacle_cli/proxy/main.py
pinnacle_cli/py/__init__.py
pinnacle_cli/py/dev_scheduler.py
pinnacle_cli/py/dev_server.py
pinnacle_cli/py/import_modules.py
pinnacle_cli/utils.py
pinnacle_cli-0.0.6.dist-info/METADATA
pinnacle_cli-0.0.6.dist-info/WHEEL
pinnacle_cli-0.0.6.dist-info/entry_points.txt
pinnacle_cli-0.0.6.dist-info/RECORD
