Metadata-Version: 2.1
Name: pinnacle-cli
Version: 0.0.6
Summary: 
Author: Ivan Zhang
Author-email: ivanzhangofficial@gmail.com
Requires-Python: >=3.12,<4.0
Classifier: Programming Language :: Python :: 3
Classifier: Programming Language :: Python :: 3.12
Requires-Dist: click (>=8.1.7,<9.0.0)
Requires-Dist: fastapi (>=0.111.0,<0.112.0)
Requires-Dist: mangum (>=0.17.0,<0.18.0)
Requires-Dist: mitmproxy (>=10.3.0,<11.0.0)
Requires-Dist: pinnacle-python (>=0.0.3,<0.0.4)
Requires-Dist: requests (>=2.32.3,<3.0.0)
Requires-Dist: schedule (>=1.2.2,<2.0.0)
